attendance_gl_src/Attendance_In_Excel.py
attendance_gl_src/Custom_Handler.py
attendance_gl_src/Excel_To_Html.py
attendance_gl_src/Runner.py
attendance_gl_src/Task_Scheduler.py
attendance_gl_src/__init__.py
attendance_gl_src/resources/config.properties
attendance_gl_src/resources/logging.conf
attendance_gl_src/resources/logo.svg
Attendance_GL-1.0.2.dist-info/METADATA
Attendance_GL-1.0.2.dist-info/WHEEL
Attendance_GL-1.0.2.dist-info/entry_points.txt
Attendance_GL-1.0.2.dist-info/top_level.txt
Attendance_GL-1.0.2.dist-info/RECORD
